calcalc/CalCalc.py
calcalc/__init__.py
calcalc_js-1.0.1.dist-info/LICENSE.txt
calcalc_js-1.0.1.dist-info/METADATA
calcalc_js-1.0.1.dist-info/WHEEL
calcalc_js-1.0.1.dist-info/top_level.txt
calcalc_js-1.0.1.dist-info/RECORD
