Metadata-Version: 2.1
Name: calcalc-js
Version: 1.0.1
Summary: A package that serves as an all purpose calculator.
Home-page: https://github.com/James11222/Astro250/tree/main/HW3
Author: James Sunseri
Author-email: jamessunseri@berkeley.edu
License: MIT
Project-URL: Bug Reports, https://github.com/James11222/Astro250/issues
Project-URL: Funding, https://donate.pypi.org
Project-URL: Check out my Website!, http://www.jamessunseri.com
Project-URL: Source, https://github.com/James11222/Astro250/tree/main/HW3/calcalc/
Keywords: calculator,simple,berkeley,cal,js
Platform: any
Classifier: Development Status :: 3 - Alpha
Classifier: Intended Audience :: Developers
Classifier: Topic :: Software Development :: Build Tools
Classifier: License :: OSI Approved :: MIT License
Classifier: Programming Language :: Python :: 3
Classifier: Programming Language :: Python :: 3.6
Classifier: Programming Language :: Python :: 3.7
Classifier: Programming Language :: Python :: 3.8
Classifier: Programming Language :: Python :: 3.9
Classifier: Programming Language :: Python :: 3.10
Classifier: Programming Language :: Python :: 3 :: Only
Requires-Python: >=3.6, <4
License-File: LICENSE.txt
Requires-Dist: requests
